{"words":[{"id":"de_technology_der_computer_1234","cat":"technology","cefr":"B1","word":"Der Computer","tr":"Bilgisayar","example":"Ich benutze den Computer.","freq":"medium","addedAt":"2025-01","source":"original"},{"id":"de_technology_das_handy_1235","cat":"technology","cefr":"B1","word":"Das Handy","tr":"Cep telefonu","example":"Mein Handy ist leer.","freq":"medium","addedAt":"2025-01","source":"original"},{"id":"de_technology_das_tablet_1236","cat":"technology","cefr":"B1","word":"Das Tablet","tr":"Tablet","example":"Ich lese auf meinem Tablet.","freq":"medium","addedAt":"2025-01","source":"original"},{"id":"de_technology_das_internet_1237","cat":"technology","cefr":"B1","word":"Das Internet","tr":"İnternet","example":"Ich suche im Internet.","freq":"medium","addedAt":"2025-01","source":"original"},{"id":"de_technology_die_webseite_1238","cat":"technology","cefr":"B1","word":"Die Webseite","tr":"Web sitesi","example":"Besuchen Sie unsere Webseite.","freq":"medium","addedAt":"2025-01","source":"original"},{"id":"de_technology_die_app_1239","cat":"technology","cefr":"B1","word":"Die App","tr":"Uygulama","example":"Ich benutze eine App.","freq":"medium","addedAt":"2025-01","source":"original"},{"id":"de_technology_das_passwort_1240","cat":"technology","cefr":"B1","word":"Das Passwort","tr":"Şifre","example":"Mein Passwort ist geheim.","freq":"medium","addedAt":"2025-01","source":"original"},{"id":"de_technology_die_e_mail_1241","cat":"technology","cefr":"B1","word":"Die E-Mail","tr":"E-posta","example":"Ich habe eine E-Mail erhalten.","freq":"medium","addedAt":"2025-01","source":"original"},{"id":"de_technology_die_sozialen_medien_1242","cat":"technology","cefr":"B1","word":"Die sozialen Medien","tr":"Sosyal medya","example":"Soziale Medien sind populär.","freq":"low","addedAt":"2025-01","source":"original"},{"id":"de_technology_die_kamera_1243","cat":"technology","cefr":"B1","word":"Die Kamera","tr":"Kamera","example":"Die Kamera nimmt auf.","freq":"medium","addedAt":"2025-01","source":"original"},{"id":"de_technology_der_fernseher_1244","cat":"technology","cefr":"B1","word":"Der Fernseher","tr":"Televizyon","example":"Wir sehen fern.","freq":"low","addedAt":"2025-01","source":"original"},{"id":"de_technology_das_radio_1245","cat":"technology","cefr":"B1","word":"Das Radio","tr":"Radyo","example":"Ich höre Radio.","freq":"medium","addedAt":"2025-01","source":"original"},{"id":"de_technology_der_drucker_1246","cat":"technology","cefr":"B1","word":"Der Drucker","tr":"Yazıcı","example":"Der Drucker ist kaputt.","freq":"medium","addedAt":"2025-01","source":"original"},{"id":"de_technology_die_tastatur_1247","cat":"technology","cefr":"B1","word":"Die Tastatur","tr":"Klavye","example":"Ich tippe auf der Tastatur.","freq":"medium","addedAt":"2025-01","source":"original"},{"id":"de_technology_die_maus_1248","cat":"technology","cefr":"B1","word":"Die Maus","tr":"Mouse (bilgisayar)","example":"Die Maus funktioniert nicht.","freq":"medium","addedAt":"2025-01","source":"original"},{"id":"de_technology_der_bildschirm_1249","cat":"technology","cefr":"B1","word":"Der Bildschirm","tr":"Ekran","example":"Der Bildschirm ist zu klein.","freq":"low","addedAt":"2025-01","source":"original"},{"id":"de_technology_der_akku_1250","cat":"technology","cefr":"B1","word":"Der Akku","tr":"Batarya","example":"Der Akku ist leer.","freq":"medium","addedAt":"2025-01","source":"original"},{"id":"de_technology_das_ladekabel_1251","cat":"technology","cefr":"B1","word":"Das Ladekabel","tr":"Şarj aleti","example":"Ich suche mein Ladekabel.","freq":"low","addedAt":"2025-01","source":"original"},{"id":"de_technology_das_wlan_1252","cat":"technology","cefr":"B1","word":"Das WLAN","tr":"Wifi","example":"Das WLAN ist langsam.","freq":"medium","addedAt":"2025-01","source":"original"},{"id":"de_technology_herunterladen_1253","cat":"technology","cefr":"B1","word":"Herunterladen","tr":"İndirmek","example":"Ich lade die Datei herunter.","freq":"low","addedAt":"2025-01","source":"original"},{"id":"de_technology_senden_1254","cat":"technology","cefr":"B1","word":"Senden","tr":"Göndermek","example":"Ich sende eine Nachricht.","freq":"high","addedAt":"2025-01","source":"original"},{"id":"de_technology_das_foto_1255","cat":"technology","cefr":"B1","word":"Das Foto","tr":"Fotoğraf","example":"Ich mache ein Foto.","freq":"medium","addedAt":"2025-01","source":"original"},{"id":"de_technology_das_video_1256","cat":"technology","cefr":"B1","word":"Das Video","tr":"Video","example":"Ich schaue ein Video.","freq":"medium","addedAt":"2025-01","source":"original"},{"id":"de_technology_die_datei_1257","cat":"technology","cefr":"B1","word":"Die Datei","tr":"Dosya","example":"Ich sende die Datei.","freq":"medium","addedAt":"2025-01","source":"original"},{"id":"de_technology_die_sicherheit_1258","cat":"technology","cefr":"B1","word":"Die Sicherheit","tr":"Güvenlik","example":"Online-Sicherheit ist wichtig.","freq":"low","addedAt":"2025-01","source":"original"},{"id":"de_technology_computer_1259","cat":"technology","cefr":"B1","word":"Computer","tr":"bilgisayar","example":"Ich arbeite am Computer jeden Tag.","freq":"medium","addedAt":"2025-01","source":"original"},{"id":"de_technology_laptop_1260","cat":"technology","cefr":"B1","word":"Laptop","tr":"laptop","example":"Mein Laptop ist sehr schnell.","freq":"medium","addedAt":"2025-01","source":"original"},{"id":"de_technology_tablette_1261","cat":"technology","cefr":"B1","word":"Tablette","tr":"tablet","example":"Die Tablette hilft gegen Kopfschmerzen.","freq":"medium","addedAt":"2025-01","source":"original"},{"id":"de_technology_smartphone_1262","cat":"technology","cefr":"B1","word":"Smartphone","tr":"akıllı telefon","example":"Ich benutze mein Smartphone oft.","freq":"medium","addedAt":"2025-01","source":"original"},{"id":"de_technology_smartwatch_1263","cat":"technology","cefr":"B1","word":"Smartwatch","tr":"akıllı saat","example":"Die Smartwatch zeigt meine Schritte an.","freq":"medium","addedAt":"2025-01","source":"original"},{"id":"de_technology_kopfhorer_1264","cat":"technology","cefr":"B1","word":"Kopfhörer","tr":"kulaklık","example":"Die Kopfhörer sind sehr bequem.","freq":"medium","addedAt":"2025-01","source":"original"},{"id":"de_technology_lautsprecher_1265","cat":"technology","cefr":"B1","word":"Lautsprecher","tr":"hoparlör","example":"Der Lautsprecher hat einen guten Klang.","freq":"medium","addedAt":"2025-01","source":"original"},{"id":"de_technology_kamera_1266","cat":"technology","cefr":"B1","word":"Kamera","tr":"kamera","example":"Die Kamera macht schöne Fotos.","freq":"medium","addedAt":"2025-01","source":"original"},{"id":"de_technology_drucker_1267","cat":"technology","cefr":"B1","word":"Drucker","tr":"yazıcı","example":"Der Drucker ist nicht angeschlossen.","freq":"medium","addedAt":"2025-01","source":"original"},{"id":"de_technology_scanner_1268","cat":"technology","cefr":"B1","word":"Scanner","tr":"tarayıcı","example":"Der Scanner liest die Dokumente ein.","freq":"medium","addedAt":"2025-01","source":"original"},{"id":"de_technology_modem_1269","cat":"technology","cefr":"B1","word":"Modem","tr":"modem","example":"Das Modem ist sehr wichtig für Internet.","freq":"medium","addedAt":"2025-01","source":"original"},{"id":"de_technology_router_1270","cat":"technology","cefr":"B1","word":"Router","tr":"router","example":"Der Router verteilt das WLAN-Signal.","freq":"medium","addedAt":"2025-01","source":"original"},{"id":"de_technology_daten_1272","cat":"technology","cefr":"B1","word":"Daten","tr":"veri","example":"Die Daten sind auf dem Computer gespeichert.","freq":"medium","addedAt":"2025-01","source":"original"},{"id":"de_technology_verschlusselung_1273","cat":"technology","cefr":"B1","word":"Verschlüsselung","tr":"şifreleme","example":"Die Verschlüsselung schützt meine Informationen.","freq":"low","addedAt":"2025-01","source":"original"},{"id":"de_technology_kunstliche_intelligenz_1274","cat":"technology","cefr":"B1","word":"künstliche Intelligenz","tr":"yapay zeka","example":"Künstliche Intelligenz verändert die Technik.","freq":"low","addedAt":"2025-01","source":"original"},{"id":"de_technology_maschinelles_lernen_1275","cat":"technology","cefr":"B1","word":"maschinelles Lernen","tr":"makine öğrenmesi","example":"Maschinelles Lernen hilft bei der Datenanalyse.","freq":"low","addedAt":"2025-01","source":"original"},{"id":"de_technology_blockchain_1276","cat":"technology","cefr":"B1","word":"Blockchain","tr":"blockchain","example":"Die Blockchain sichert die Transaktionen.","freq":"medium","addedAt":"2025-01","source":"original"},{"id":"de_technology_virtuelle_realitat_1277","cat":"technology","cefr":"B1","word":"virtuelle Realität","tr":"sanal gerçeklik","example":"Virtuelle Realität ist sehr spannend.","freq":"low","addedAt":"2025-01","source":"original"},{"id":"de_technology_augmented_reality_1278","cat":"technology","cefr":"B1","word":"Augmented Reality","tr":"artırılmış gerçeklik","example":"Augmented Reality ist eine neue Technologie.","freq":"low","addedAt":"2025-01","source":"original"},{"id":"de_technology_anwendung_1279","cat":"technology","cefr":"B1","word":"ANWENDUNG","tr":"uygulama","example":"Die Anwendung ist einfach zu bedienen.","freq":"medium","addedAt":"2025-01","source":"original"},{"id":"de_technology_software_1280","cat":"technology","cefr":"B1","word":"Software","tr":"yazılım","example":"Die Software muss aktualisiert werden.","freq":"medium","addedAt":"2025-01","source":"original"},{"id":"de_technology_prozessor_1282","cat":"technology","cefr":"B1","word":"Prozessor","tr":"işlemci","example":"Der Prozessor ist das Herz des Computers.","freq":"medium","addedAt":"2025-01","source":"original"},{"id":"de_technology_erinnerung_1283","cat":"technology","cefr":"B1","word":"Erinnerung","tr":"bellek","example":"Die Erinnerung ist sehr wichtig für mich.","freq":"medium","addedAt":"2025-01","source":"original"},{"id":"de_technology_lagerung_1284","cat":"technology","cefr":"B1","word":"Lagerung","tr":"depolama","example":"Die Lagerung der Daten ist sicher.","freq":"medium","addedAt":"2025-01","source":"original"},{"id":"de_technology_batterie_1285","cat":"technology","cefr":"B1","word":"Batterie","tr":"batarya","example":"Die Batterie ist fast leer.","freq":"medium","addedAt":"2025-01","source":"original"},{"id":"de_technology_aufladung_1286","cat":"technology","cefr":"B1","word":"Aufladung","tr":"şarj","example":"Die Aufladung dauert nicht lange.","freq":"medium","addedAt":"2025-01","source":"original"},{"id":"de_technology_verbindung_1287","cat":"technology","cefr":"B1","word":"Verbindung","tr":"bağlantı","example":"Die Verbindung ist sehr stabil.","freq":"medium","addedAt":"2025-01","source":"original"},{"id":"de_technology_sicherheit_1288","cat":"technology","cefr":"B1","word":"Sicherheit","tr":"güvenlik","example":"Die Sicherheit meiner Daten ist wichtig.","freq":"medium","addedAt":"2025-01","source":"original"},{"id":"de_environment_die_umweltverschmutzung_1562","cat":"environment","cefr":"B1","word":"Die Umweltverschmutzung","tr":"Kirlilik","example":"Die Umweltverschmutzung nimmt zu.","freq":"low","addedAt":"2025-01","source":"original"},{"id":"de_environment_der_klimawandel_1563","cat":"environment","cefr":"B1","word":"Der Klimawandel","tr":"İklim değişikliği","example":"Der Klimawandel ist ernst.","freq":"low","addedAt":"2025-01","source":"original"},{"id":"de_environment_die_luft_1564","cat":"environment","cefr":"B1","word":"Die Luft","tr":"Hava (solunan)","example":"Die Luft ist frisch.","freq":"medium","addedAt":"2025-01","source":"original"},{"id":"de_environment_die_energie_1565","cat":"environment","cefr":"B1","word":"Die Energie","tr":"Enerji","example":"Wir sparen Energie.","freq":"medium","addedAt":"2025-01","source":"original"},{"id":"de_environment_die_elektrizitat_1566","cat":"environment","cefr":"B1","word":"Die Elektrizität","tr":"Elektrik","example":"Der Strom ist ausgefallen.","freq":"low","addedAt":"2025-01","source":"original"},{"id":"de_environment_die_erneuerbare_energie_1567","cat":"environment","cefr":"B1","word":"Die erneuerbare Energie","tr":"Yenilenebilir enerji","example":"Erneuerbare Energie ist grün.","freq":"low","addedAt":"2025-01","source":"original"},{"id":"de_environment_das_recycling_1568","cat":"environment","cefr":"B1","word":"Das Recycling","tr":"Geri dönüşüm","example":"Recycling ist wichtig.","freq":"low","addedAt":"2025-01","source":"original"},{"id":"de_environment_der_mull_1569","cat":"environment","cefr":"B1","word":"Der Müll","tr":"Çöp / Atık","example":"Müll trennen.","freq":"medium","addedAt":"2025-01","source":"original"},{"id":"de_environment_die_artenvielfalt_1570","cat":"environment","cefr":"B1","word":"Die Artenvielfalt","tr":"Biyoçeşitlilik","example":"Die Artenvielfalt ist bedroht.","freq":"low","addedAt":"2025-01","source":"original"},{"id":"de_environment_die_bedrohte_art_1571","cat":"environment","cefr":"B1","word":"Die bedrohte Art","tr":"Nesli tükenmekte olan tür","example":"Der Adler ist eine bedrohte Art.","freq":"low","addedAt":"2025-01","source":"original"},{"id":"de_environment_die_nachhaltige_entwicklung_1572","cat":"environment","cefr":"B1","word":"Die nachhaltige Entwicklung","tr":"Sürdürülebilir kalkınma","example":"Nachhaltige Entwicklung ist wichtig.","freq":"low","addedAt":"2025-01","source":"original"},{"id":"de_environment_die_okologie_1573","cat":"environment","cefr":"B1","word":"Die Ökologie","tr":"Ekoloji","example":"Ökologie ist eine Wissenschaft.","freq":"medium","addedAt":"2025-01","source":"original"},{"id":"de_environment_die_umwelt_1574","cat":"environment","cefr":"B1","word":"Die Umwelt","tr":"Çevre","example":"Lasst uns die Umwelt schützen.","freq":"medium","addedAt":"2025-01","source":"original"},{"id":"de_environment_die_uberschwemmung_1575","cat":"environment","cefr":"B1","word":"Die Überschwemmung","tr":"Sel / Taşkın","example":"Die Überschwemmung zerstörte Häuser.","freq":"low","addedAt":"2025-01","source":"original"},{"id":"de_environment_die_durre_1576","cat":"environment","cefr":"B1","word":"Die Dürre","tr":"Kuraklık","example":"Die Dürre dauert seit Monaten.","freq":"medium","addedAt":"2025-01","source":"original"},{"id":"de_environment_das_kompostieren_1577","cat":"environment","cefr":"B1","word":"Das Kompostieren","tr":"Kompostlama","example":"Kompostieren reduziert Müll.","freq":"low","addedAt":"2025-01","source":"original"},{"id":"de_environment_der_co2_fu_abdruck_1578","cat":"environment","cefr":"B1","word":"Der CO2-Fußabdruck","tr":"Karbon ayak izi","example":"Ich reduziere meinen CO2-Fußabdruck.","freq":"low","addedAt":"2025-01","source":"original"},{"id":"de_environment_das_solarpanel_1579","cat":"environment","cefr":"B1","word":"Das Solarpanel","tr":"Güneş paneli","example":"Solarpanele erzeugen Energie.","freq":"low","addedAt":"2025-01","source":"original"},{"id":"de_environment_die_windturbine_1580","cat":"environment","cefr":"B1","word":"Die Windturbine","tr":"Rüzgar türbini","example":"Windturbinen erzeugen Strom.","freq":"low","addedAt":"2025-01","source":"original"},{"id":"de_environment_die_abholzung_1581","cat":"environment","cefr":"B1","word":"Die Abholzung","tr":"Ormansızlaşma","example":"Abholzung ist gefährlich.","freq":"low","addedAt":"2025-01","source":"original"},{"id":"de_environment_das_co2_1582","cat":"environment","cefr":"B1","word":"Das CO2","tr":"Karbondioksit","example":"CO2 erwärmt den Planeten.","freq":"medium","addedAt":"2025-01","source":"original"},{"id":"de_environment_der_planet_1583","cat":"environment","cefr":"B1","word":"Der Planet","tr":"Gezegen","example":"Lasst uns unseren Planeten schützen.","freq":"medium","addedAt":"2025-01","source":"original"},{"id":"de_environment_das_trinkwasser_1584","cat":"environment","cefr":"B1","word":"Das Trinkwasser","tr":"İçme suyu","example":"Trinkwasser ist kostbar.","freq":"low","addedAt":"2025-01","source":"original"},{"id":"de_environment_biologisch_abbaubar_1585","cat":"environment","cefr":"B1","word":"Biologisch abbaubar","tr":"Biyolojik olarak bozunabilir","example":"Biologisch abbaubare Verpackung.","freq":"low","addedAt":"2025-01","source":"original"},{"id":"de_environment_die_nachhaltigkeit_1586","cat":"environment","cefr":"B1","word":"Die Nachhaltigkeit","tr":"Sürdürülebilirlik","example":"Nachhaltigkeit ist unser Ziel.","freq":"low","addedAt":"2025-01","source":"original"},{"id":"de_environment_luftverschmutzung_1587","cat":"environment","cefr":"B1","word":"Luftverschmutzung","tr":"hava kirliliği","example":"Die Luftverschmutzung ist ein großes Problem.","freq":"low","addedAt":"2025-01","source":"original"},{"id":"de_environment_wasserverschmutzung_1588","cat":"environment","cefr":"B1","word":"Wasserverschmutzung","tr":"su kirliliği","example":"Wasserverschmutzung schadet der Umwelt.","freq":"low","addedAt":"2025-01","source":"original"},{"id":"de_environment_bodenverschmutzung_1589","cat":"environment","cefr":"B1","word":"Bodenverschmutzung","tr":"toprak kirliliği","example":"Bodenverschmutzung betrifft unsere Lebensmittel.","freq":"low","addedAt":"2025-01","source":"original"},{"id":"de_environment_larmbelastigung_1590","cat":"environment","cefr":"B1","word":"Lärmbelästigung","tr":"gürültü kirliliği","example":"Lärmbelästigung kann sehr störend sein.","freq":"low","addedAt":"2025-01","source":"original"},{"id":"de_environment_plastikmull_1591","cat":"environment","cefr":"B1","word":"Plastikmüll","tr":"plastik atık","example":"Plastikmüll ist ein ernstes Umweltproblem.","freq":"medium","addedAt":"2025-01","source":"original"},{"id":"de_environment_elektroschrott_1592","cat":"environment","cefr":"B1","word":"Elektroschrott","tr":"elektronik atık","example":"Elektroschrott muss richtig entsorgt werden.","freq":"low","addedAt":"2025-01","source":"original"},{"id":"de_environment_treibhausgas_1593","cat":"environment","cefr":"B1","word":"Treibhausgas","tr":"sera gazı","example":"Treibhausgase schädigen unser Klima.","freq":"medium","addedAt":"2025-01","source":"original"},{"id":"de_environment_co2_fu_abdruck_1594","cat":"environment","cefr":"B1","word":"CO2-Fußabdruck","tr":"karbon ayak izi","example":"Der CO2-Fußabdruck ist wichtig zu beachten.","freq":"low","addedAt":"2025-01","source":"original"},{"id":"de_environment_globale_erwarmung_1595","cat":"environment","cefr":"B1","word":"globale Erwärmung","tr":"küresel ısınma","example":"Globale Erwärmung betrifft uns alle.","freq":"low","addedAt":"2025-01","source":"original"},{"id":"de_environment_klimawandel_1596","cat":"environment","cefr":"B1","word":"Klimawandel","tr":"iklim değişikliği","example":"Der Klimawandel verändert unser Wetter.","freq":"medium","addedAt":"2025-01","source":"original"},{"id":"de_environment_ozonschicht_1597","cat":"environment","cefr":"B1","word":"Ozonschicht","tr":"ozon tabakası","example":"Die Ozonschicht schützt uns vor der Sonne.","freq":"medium","addedAt":"2025-01","source":"original"},{"id":"de_environment_saurer_regen_1598","cat":"environment","cefr":"B1","word":"saurer Regen","tr":"asit yağmuru","example":"Saurer Regen schadet Bäumen und Pflanzen.","freq":"medium","addedAt":"2025-01","source":"original"},{"id":"de_environment_abholzung_1599","cat":"environment","cefr":"B1","word":"Abholzung","tr":"ormansızlaşma","example":"Abholzung gefährdet viele Tierarten.","freq":"medium","addedAt":"2025-01","source":"original"},{"id":"de_environment_erosion_1600","cat":"environment","cefr":"B1","word":"Erosion","tr":"erozyon","example":"Erosion kann Landflächen zerstören.","freq":"medium","addedAt":"2025-01","source":"original"},{"id":"de_environment_wustenbildung_1601","cat":"environment","cefr":"B1","word":"Wüstenbildung","tr":"çölleşme","example":"Wüstenbildung ist ein Problem in vielen Ländern.","freq":"low","addedAt":"2025-01","source":"original"},{"id":"de_environment_verlust_der_artenvielfalt_1602","cat":"environment","cefr":"B1","word":"Verlust der Artenvielfalt","tr":"biyoçeşitlilik kaybı","example":"Der Verlust der Artenvielfalt ist alarmierend.","freq":"low","addedAt":"2025-01","source":"original"},{"id":"de_environment_gefahrdete_arten_1603","cat":"environment","cefr":"B1","word":"gefährdete Arten","tr":"nesli tükenmekte olan türler","example":"Gefährdete Arten brauchen unseren Schutz.","freq":"low","addedAt":"2025-01","source":"original"},{"id":"de_environment_erneuerbare_energie_1604","cat":"environment","cefr":"B1","word":"erneuerbare Energie","tr":"yenilenebilir enerji","example":"Erneuerbare Energie ist die Zukunft.","freq":"low","addedAt":"2025-01","source":"original"},{"id":"de_environment_sonnenenergie_1605","cat":"environment","cefr":"B1","word":"Sonnenenergie","tr":"güneş enerjisi","example":"Sonnenenergie ist eine saubere Energiequelle.","freq":"low","addedAt":"2025-01","source":"original"},{"id":"de_environment_windenergie_1606","cat":"environment","cefr":"B1","word":"Windenergie","tr":"rüzgar enerjisi","example":"Windenergie ist umweltfreundlich und nachhaltig.","freq":"medium","addedAt":"2025-01","source":"original"},{"id":"de_environment_kernenergie_1607","cat":"environment","cefr":"B1","word":"Kernenergie","tr":"nükleer enerji","example":"Kernenergie hat Vor- und Nachteile.","freq":"medium","addedAt":"2025-01","source":"original"},{"id":"de_environment_recyceln_1608","cat":"environment","cefr":"B1","word":"recyceln","tr":"geri dönüşüm","example":"Wir sollten mehr recyceln für die Umwelt.","freq":"medium","addedAt":"2025-01","source":"original"},{"id":"de_environment_kompost_1609","cat":"environment","cefr":"B1","word":"Kompost","tr":"kompost","example":"Kompost ist gut für den Garten.","freq":"medium","addedAt":"2025-01","source":"original"},{"id":"de_environment_nachhaltigkeit_1610","cat":"environment","cefr":"B1","word":"Nachhaltigkeit","tr":"sürdürülebilirlik","example":"Nachhaltigkeit ist wichtig für kommende Generationen.","freq":"low","addedAt":"2025-01","source":"original"},{"id":"de_environment_okologie_1611","cat":"environment","cefr":"B1","word":"Ökologie","tr":"ekoloji","example":"Die Ökologie ist wichtig für unsere Umwelt.","freq":"medium","addedAt":"2025-01","source":"original"},{"id":"de_environment_naturschutz_1612","cat":"environment","cefr":"B1","word":"Naturschutz","tr":"doğa koruma","example":"Der Naturschutz schützt die Tiere und Pflanzen.","freq":"medium","addedAt":"2025-01","source":"original"},{"id":"de_environment_nationalpark_1613","cat":"environment","cefr":"B1","word":"Nationalpark","tr":"milli park","example":"Der Nationalpark ist ein schöner Ort zum Wandern.","freq":"medium","addedAt":"2025-01","source":"original"},{"id":"de_environment_naturschutzgebiet_1614","cat":"environment","cefr":"B1","word":"Naturschutzgebiet","tr":"doğal rezerv","example":"Das Naturschutzgebiet ist für seltene Arten wichtig.","freq":"low","addedAt":"2025-01","source":"original"},{"id":"de_media_die_zeitung_1615","cat":"media","cefr":"B1","word":"Die Zeitung","tr":"Gazete","example":"Ich lese die Zeitung.","freq":"medium","addedAt":"2025-01","source":"original"},{"id":"de_media_das_magazin_1616","cat":"media","cefr":"B1","word":"Das Magazin","tr":"Dergi","example":"Ich kaufe ein Magazin.","freq":"medium","addedAt":"2025-01","source":"original"},{"id":"de_media_der_bericht_1617","cat":"media","cefr":"B1","word":"Der Bericht","tr":"Haber / Röportaj","example":"Ein Bericht über den Krieg.","freq":"medium","addedAt":"2025-01","source":"original"},{"id":"de_media_die_nachrichten_1618","cat":"media","cefr":"B1","word":"Die Nachrichten","tr":"Güncel haberler","example":"Ich verfolge die Nachrichten.","freq":"low","addedAt":"2025-01","source":"original"},{"id":"de_media_die_werbung_1619","cat":"media","cefr":"B1","word":"Die Werbung","tr":"Reklam","example":"Es gibt zu viel Werbung.","freq":"medium","addedAt":"2025-01","source":"original"},{"id":"de_media_die_dokumentation_1620","cat":"media","cefr":"B1","word":"Die Dokumentation","tr":"Belgesel","example":"Ich liebe Dokumentationen.","freq":"low","addedAt":"2025-01","source":"original"},{"id":"de_media_der_film_1621","cat":"media","cefr":"B1","word":"Der Film","tr":"Film","example":"Wir schauen einen Film.","freq":"medium","addedAt":"2025-01","source":"original"},{"id":"de_media_die_serie_1622","cat":"media","cefr":"B1","word":"Die Serie","tr":"Dizi","example":"Ich liebe diese Serie.","freq":"medium","addedAt":"2025-01","source":"original"},{"id":"de_media_der_podcast_1623","cat":"media","cefr":"B1","word":"Der Podcast","tr":"Podcast","example":"Ich höre einen Podcast.","freq":"medium","addedAt":"2025-01","source":"original"},{"id":"de_media_die_sozialen_netzwerke_1624","cat":"media","cefr":"B1","word":"Die sozialen Netzwerke","tr":"Sosyal ağlar","example":"Soziale Netzwerke beeinflussen uns.","freq":"low","addedAt":"2025-01","source":"original"},{"id":"de_media_der_artikel_1625","cat":"media","cefr":"B1","word":"Der Artikel","tr":"Makale / Haber","example":"Ich habe einen interessanten Artikel gelesen.","freq":"medium","addedAt":"2025-01","source":"original"},{"id":"de_media_das_interview_1626","cat":"media","cefr":"B1","word":"Das Interview","tr":"Röportaj / Mülakat","example":"Das Interview war fesselnd.","freq":"low","addedAt":"2025-01","source":"original"},{"id":"de_media_die_pressekonferenz_1627","cat":"media","cefr":"B1","word":"Die Pressekonferenz","tr":"Basın toplantısı","example":"Der Minister hält eine Pressekonferenz.","freq":"low","addedAt":"2025-01","source":"original"},{"id":"de_media_die_debatte_1628","cat":"media","cefr":"B1","word":"Die Debatte","tr":"Tartışma / Münazara","example":"Die Debatte ist lebhaft.","freq":"medium","addedAt":"2025-01","source":"original"},{"id":"de_media_die_information_1629","cat":"media","cefr":"B1","word":"Die Information","tr":"Bilgi / Haber","example":"Das ist eine wichtige Information.","freq":"low","addedAt":"2025-01","source":"original"},{"id":"de_media_der_kanal_1630","cat":"media","cefr":"B1","word":"Der Kanal","tr":"Kanal","example":"Welchen Kanal schaust du?","freq":"medium","addedAt":"2025-01","source":"original"},{"id":"de_media_das_abonnement_1631","cat":"media","cefr":"B1","word":"Das Abonnement","tr":"Abonelik","example":"Ich habe ein Abonnement.","freq":"low","addedAt":"2025-01","source":"original"},{"id":"de_media_die_sendung_1632","cat":"media","cefr":"B1","word":"Die Sendung","tr":"Yayın","example":"Die Sendung ist live.","freq":"medium","addedAt":"2025-01","source":"original"},{"id":"de_media_die_schlagzeile_1633","cat":"media","cefr":"B1","word":"Die Schlagzeile","tr":"Manşet / Birinci sayfa","example":"Die Nachricht ist auf der Titelseite.","freq":"low","addedAt":"2025-01","source":"original"},{"id":"de_media_die_meinung_1634","cat":"media","cefr":"B1","word":"Die Meinung","tr":"Görüş / Kanaat","example":"Was ist deine Meinung?","freq":"medium","addedAt":"2025-01","source":"original"},{"id":"de_media_das_streaming_1635","cat":"media","cefr":"B1","word":"Das Streaming","tr":"Yayın akışı","example":"Ich schaue per Streaming.","freq":"low","addedAt":"2025-01","source":"original"},{"id":"de_media_der_hashtag_1636","cat":"media","cefr":"B1","word":"Der Hashtag","tr":"Hashtag","example":"Dieser Hashtag ist im Trend.","freq":"medium","addedAt":"2025-01","source":"original"},{"id":"de_media_der_trend_1637","cat":"media","cefr":"B1","word":"Der Trend","tr":"Trend","example":"Das ist ein aktueller Trend.","freq":"medium","addedAt":"2025-01","source":"original"},{"id":"de_media_der_blog_1638","cat":"media","cefr":"B1","word":"Der Blog","tr":"Blog","example":"Ich schreibe einen Blog.","freq":"medium","addedAt":"2025-01","source":"original"},{"id":"de_media_zeitung_1640","cat":"media","cefr":"B1","word":"Zeitung","tr":"gazete","example":"Ich lese jeden Morgen die Zeitung bei Frühstück.","freq":"medium","addedAt":"2025-01","source":"original"},{"id":"de_media_magazin_1641","cat":"media","cefr":"B1","word":"Magazin","tr":"dergi","example":"Das Magazin hat viele interessante Artikel.","freq":"medium","addedAt":"2025-01","source":"original"},{"id":"de_media_fernsehen_1642","cat":"media","cefr":"B1","word":"Fernsehen","tr":"televizyon","example":"Ich schaue jeden Abend Fernsehen mit meiner Familie.","freq":"medium","addedAt":"2025-01","source":"original"},{"id":"de_media_radio_1643","cat":"media","cefr":"B1","word":"Radio","tr":"radyo","example":"Das Radio spielt meine Lieblingsmusik den ganzen Tag.","freq":"medium","addedAt":"2025-01","source":"original"},{"id":"de_media_podcast_1644","cat":"media","cefr":"B1","word":"Podcast","tr":"podcast","example":"Ich höre oft einen Podcast über Wissenschaft.","freq":"medium","addedAt":"2025-01","source":"original"},{"id":"de_media_blog_1645","cat":"media","cefr":"B1","word":"Blog","tr":"blog","example":"Mein Freund hat einen Blog über Reisen.","freq":"medium","addedAt":"2025-01","source":"original"},{"id":"de_media_vlog_1646","cat":"media","cefr":"B1","word":"Vlog","tr":"vlog","example":"Sie macht einen Vlog über ihr Leben.","freq":"medium","addedAt":"2025-01","source":"original"},{"id":"de_media_soziale_medien_1647","cat":"media","cefr":"B1","word":"soziale Medien","tr":"sosyal medya","example":"Soziale Medien verbinden Menschen auf der ganzen Welt.","freq":"low","addedAt":"2025-01","source":"original"},{"id":"de_media_instagram_1648","cat":"media","cefr":"B1","word":"Instagram","tr":"instagram","example":"Ich poste oft Bilder auf Instagram.","freq":"medium","addedAt":"2025-01","source":"original"},{"id":"de_media_twitter_1649","cat":"media","cefr":"B1","word":"Twitter","tr":"twitter","example":"Er tweetet Nachrichten auf Twitter jeden Tag.","freq":"medium","addedAt":"2025-01","source":"original"},{"id":"de_media_youtube_1650","cat":"media","cefr":"B1","word":"youtube","tr":"youtube","example":"Ich schaue viele Videos auf YouTube.","freq":"medium","addedAt":"2025-01","source":"original"},{"id":"de_media_tiktok_1651","cat":"media","cefr":"B1","word":"Tiktok","tr":"tiktok","example":"Tiktok ist eine beliebte Plattform für kurze Videos.","freq":"medium","addedAt":"2025-01","source":"original"},{"id":"de_media_facebook_1652","cat":"media","cefr":"B1","word":"Facebook","tr":"facebook","example":"Facebook wird von vielen Menschen genutzt.","freq":"medium","addedAt":"2025-01","source":"original"},{"id":"de_media_whatsapp_1653","cat":"media","cefr":"B1","word":"WhatsApp","tr":"whatsapp","example":"Ich chatte mit Freunden über WhatsApp.","freq":"medium","addedAt":"2025-01","source":"original"},{"id":"de_media_telegramm_1654","cat":"media","cefr":"B1","word":"Telegramm","tr":"telegram","example":"Wir kommunizieren über Telegramm in Gruppen.","freq":"medium","addedAt":"2025-01","source":"original"},{"id":"de_media_nachricht_1655","cat":"media","cefr":"B1","word":"Nachricht","tr":"haber","example":"Die Nachricht über das Wetter ist wichtig.","freq":"medium","addedAt":"2025-01","source":"original"},{"id":"de_media_manschette_1656","cat":"media","cefr":"B1","word":"Manschette","tr":"manşet","example":"Die Manschette der Zeitung ist sehr auffällig.","freq":"medium","addedAt":"2025-01","source":"original"},{"id":"de_media_bericht_1657","cat":"media","cefr":"B1","word":"Bericht","tr":"röportaj","example":"Der Bericht über das Konzert war sehr spannend.","freq":"medium","addedAt":"2025-01","source":"original"},{"id":"de_media_dokumentarfilm_1658","cat":"media","cefr":"B1","word":"Dokumentarfilm","tr":"belgesel","example":"Der Dokumentarfilm zeigt die Schönheit der Natur.","freq":"low","addedAt":"2025-01","source":"original"},{"id":"de_media_seifenoper_1659","cat":"media","cefr":"B1","word":"Seifenoper","tr":"dizi","example":"Die Seifenoper hat viele treue Zuschauer.","freq":"medium","addedAt":"2025-01","source":"original"},{"id":"de_media_film_1660","cat":"media","cefr":"B1","word":"Film","tr":"film","example":"Der Film war sehr unterhaltsam und spannend.","freq":"medium","addedAt":"2025-01","source":"original"},{"id":"de_media_animation_1661","cat":"media","cefr":"B1","word":"Animation","tr":"animasyon","example":"Die Animation war bunt und lebendig.","freq":"medium","addedAt":"2025-01","source":"original"},{"id":"de_media_hinweisen_1662","cat":"media","cefr":"B1","word":"hinweisen","tr":"reklam","example":"Ich möchte auf die Vorteile hinweisen.","freq":"medium","addedAt":"2025-01","source":"original"},{"id":"de_media_propaganda_1663","cat":"media","cefr":"B1","word":"Propaganda","tr":"propaganda","example":"Die Propaganda beeinflusst die Meinungen der Menschen.","freq":"medium","addedAt":"2025-01","source":"original"},{"id":"de_media_zensur_1664","cat":"media","cefr":"B1","word":"Zensur","tr":"sansür","example":"Zensur ist in vielen Ländern ein großes Problem.","freq":"medium","addedAt":"2025-01","source":"original"},{"id":"de_media_pressefreiheit_1665","cat":"media","cefr":"B1","word":"Pressefreiheit","tr":"basın özgürlüğü","example":"Die Pressefreiheit ist wichtig für die Demokratie.","freq":"low","addedAt":"2025-01","source":"original"},{"id":"de_media_korrespondent_1666","cat":"media","cefr":"B1","word":"Korrespondent","tr":"muhabir","example":"Der Korrespondent berichtet aus verschiedenen Ländern.","freq":"low","addedAt":"2025-01","source":"original"},{"id":"de_media_streaming_1668","cat":"media","cefr":"B1","word":"Streaming","tr":"yayın akışı","example":"Streaming von Filmen wird immer beliebter.","freq":"medium","addedAt":"2025-01","source":"original"},{"id":"de_media_schopfer_1669","cat":"media","cefr":"B1","word":"Schöpfer","tr":"içerik üretici","example":"Der Schöpfer dieses Videos ist sehr kreativ.","freq":"medium","addedAt":"2025-01","source":"original"},{"id":"de_media_die_presse_2122","cat":"media","cefr":"A1","word":"die Presse","tr":"basın","example":"Die Presse berichtet viel.","freq":"high","addedAt":"2026-04","source":"popmots"},{"id":"de_technology_die_maschine_2125","cat":"technology","cefr":"A1","word":"die Maschine","tr":"makine","example":"Die Maschine funktioniert gut.","freq":"high","addedAt":"2026-04","source":"popmots"},{"id":"de_technology_das_gerat_2134","cat":"technology","cefr":"A2","word":"das Gerät","tr":"aparatus","example":"Das Gerät ist neu.","freq":"medium","addedAt":"2026-04","source":"popmots"},{"id":"de_technology_der_motor_2405","cat":"technology","cefr":"A2","word":"der Motor","tr":"motor","example":"Der Motor des Autos ist sehr laut.","freq":"medium","addedAt":"2026-04","source":"popmots"},{"id":"de_technology_elektrisch_2826","cat":"technology","cefr":"A2","word":"elektrisch","tr":"elektrik","example":"Die Lampe ist elektrisch und sehr hell.","freq":"medium","addedAt":"2026-04","source":"popmots"},{"id":"de_media_die_filmaufnahme_2839","cat":"media","cefr":"A2","word":"die Filmaufnahme","tr":"çekim","example":"Die Filmaufnahme war sehr erfolgreich.","freq":"medium","addedAt":"2026-04","source":"popmots"},{"id":"de_media_die_episode_2988","cat":"media","cefr":"A2","word":"die Episode","tr":"bölüm","example":"Die Episode war sehr spannend und interessant.","freq":"medium","addedAt":"2026-04","source":"popmots"},{"id":"de_media_das_publikum_3001","cat":"media","cefr":"A2","word":"das Publikum","tr":"izleyici","example":"Das Publikum applaudiert nach der Aufführung.","freq":"medium","addedAt":"2026-04","source":"popmots"},{"id":"de_technology_technisch_3165","cat":"technology","cefr":"B1","word":"technisch","tr":"teknik","example":"Technisch gesehen ist das Gerät sehr fortschrittlich.","freq":"low","addedAt":"2026-04","source":"popmots"},{"id":"de_technology_das_radar_3639","cat":"technology","cefr":"B1","word":"das Radar","tr":"radar","example":"Das Radar zeigt ein Flugzeug an.","freq":"low","addedAt":"2026-04","source":"popmots"},{"id":"de_media_die_ausgabe_3674","cat":"media","cefr":"B1","word":"die Ausgabe","tr":"yayın","example":"Die Ausgabe der Zeitung ist heute erschienen.","freq":"low","addedAt":"2026-04","source":"popmots"},{"id":"de_technology_der_generator_4006","cat":"technology","cefr":"B1","word":"der Generator","tr":"jeneratör","example":"Der Generator liefert Strom für das Haus.","freq":"low","addedAt":"2026-04","source":"popmots"},{"id":"de_technology_telefonisch_4109","cat":"technology","cefr":"B1","word":"telefonisch","tr":"telefon","example":"Wir haben telefonisch einen Termin vereinbart.","freq":"low","addedAt":"2026-04","source":"popmots"},{"id":"de_technology_der_laser_4159","cat":"technology","cefr":"B1","word":"der Laser","tr":"lazer","example":"Der Laser wird in vielen Technologien eingesetzt.","freq":"low","addedAt":"2026-04","source":"popmots"},{"id":"de_technology_das_fax_4252","cat":"technology","cefr":"B1","word":"das Fax","tr":"faks","example":"Ich habe das Fax an die Firma geschickt.","freq":"low","addedAt":"2026-04","source":"popmots"},{"id":"de_media_das_plakat_4316","cat":"media","cefr":"B1","word":"das Plakat","tr":"afiş","example":"Das Plakat hängt an der Wand.","freq":"low","addedAt":"2026-04","source":"popmots"},{"id":"de_media_der_western_4388","cat":"media","cefr":"B1","word":"der Western","tr":"western","example":"Der Western ist ein beliebtes Filmgenre.","freq":"low","addedAt":"2026-04","source":"popmots"},{"id":"de_media_die_exklusivmeldung_4410","cat":"media","cefr":"B1","word":"die Exklusivmeldung","tr":"özel haber","example":"Die Exklusivmeldung hat alle überrascht.","freq":"low","addedAt":"2026-04","source":"popmots"},{"id":"de_technology_elektronisch_4447","cat":"technology","cefr":"B1","word":"elektronisch","tr":"elektronik","example":"Die elektronisch gesteuerten Geräte sind praktisch.","freq":"low","addedAt":"2026-04","source":"popmots"},{"id":"de_technology_die_informatik_4612","cat":"technology","cefr":"B1","word":"die Informatik","tr":"bilgisayar bilimi","example":"Die Informatik ist ein spannendes Fachgebiet.","freq":"low","addedAt":"2026-04","source":"popmots"},{"id":"de_technology_der_zahler_4743","cat":"technology","cefr":"B1","word":"der Zähler","tr":"sayacı","example":"Der Zähler zeigt die genaue Anzahl der Besucher an.","freq":"low","addedAt":"2026-04","source":"popmots"},{"id":"de_technology_die_fernbedienung_4876","cat":"technology","cefr":"B1","word":"die Fernbedienung","tr":"uzaktan kumanda","example":"Die Fernbedienung funktioniert nicht mehr richtig.","freq":"low","addedAt":"2026-04","source":"popmots"},{"id":"de_technology_der_mechanismus_5000","cat":"technology","cefr":"B2","word":"der Mechanismus","tr":"mekanizma","example":"Der Mechanismus funktioniert einwandfrei.","freq":"low","addedAt":"2026-04","source":"popmots"},{"id":"de_technology_der_reaktor_5100","cat":"technology","cefr":"B2","word":"der Reaktor","tr":"reaktör","example":"Der Reaktor wird regelmäßig gewartet und überprüft.","freq":"low","addedAt":"2026-04","source":"popmots"},{"id":"de_technology_die_synchronisation_5137","cat":"technology","cefr":"B2","word":"die Synchronisation","tr":"senkronizasyon","example":"Die Synchronisation der Filme war sehr gelungen.","freq":"low","addedAt":"2026-04","source":"popmots"},{"id":"de_media_der_prominente_5153","cat":"media","cefr":"B2","word":"der Prominente","tr":"ünlü","example":"Der prominente Schauspieler kam zu unserer Veranstaltung.","freq":"low","addedAt":"2026-04","source":"popmots"},{"id":"de_media_der_journalismus_5358","cat":"media","cefr":"B2","word":"der Journalismus","tr":"gazetecilik","example":"Der Journalismus spielt eine wichtige Rolle in der Gesellschaft.","freq":"low","addedAt":"2026-04","source":"popmots"},{"id":"de_technology_der_projektor_5457","cat":"technology","cefr":"B2","word":"der Projektor","tr":"projektör","example":"Der Projektor zeigt den Film sehr klar.","freq":"low","addedAt":"2026-04","source":"popmots"},{"id":"de_technology_mechanisch_5670","cat":"technology","cefr":"B2","word":"mechanisch","tr":"mekanik","example":"Die mechanischen Teile der Uhr müssen regelmäßig gewartet werden.","freq":"low","addedAt":"2026-04","source":"popmots"},{"id":"de_technology_der_lautsprecher_5868","cat":"technology","cefr":"B2","word":"der Lautsprecher","tr":"hoparlör","example":"Der Lautsprecher hat eine hervorragende Klangqualität.","freq":"low","addedAt":"2026-04","source":"popmots"},{"id":"de_technology_der_schalter_5898","cat":"technology","cefr":"B2","word":"der Schalter","tr":"anahtar","example":"Der Schalter befindet sich an der Wand links.","freq":"low","addedAt":"2026-04","source":"popmots"},{"id":"de_media_die_ausstrahlung_5934","cat":"media","cefr":"B2","word":"die Ausstrahlung","tr":"yayın","example":"Die Ausstrahlung des neuen Programms beginnt um 20 Uhr.","freq":"low","addedAt":"2026-04","source":"popmots"},{"id":"de_environment_die_verschmutzung_6128","cat":"environment","cefr":"B2","word":"die Verschmutzung","tr":"kirlilik","example":"Die Verschmutzung der Luft ist ein großes Problem.","freq":"low","addedAt":"2026-04","source":"popmots"},{"id":"de_media_die_umfrage_6146","cat":"media","cefr":"B2","word":"die Umfrage","tr":"anket","example":"Die Umfrage ergab interessante Ergebnisse über die Meinungen.","freq":"low","addedAt":"2026-04","source":"popmots"},{"id":"de_technology_der_kopierer_6203","cat":"technology","cefr":"B2","word":"der Kopierer","tr":"fotokopi makinesi","example":"Der Kopierer funktioniert nicht richtig und muss repariert werden.","freq":"low","addedAt":"2026-04","source":"popmots"},{"id":"de_technology_der_kassettenrekorder_6214","cat":"technology","cefr":"B2","word":"der Kassettenrekorder","tr":"ses kaydedici","example":"Der Kassettenrekorder spielt meine Lieblingsmusik ab.","freq":"low","addedAt":"2026-04","source":"popmots"},{"id":"de_technology_der_zoom_6217","cat":"technology","cefr":"B2","word":"der Zoom","tr":"yakınlaştırma","example":"Der Zoom der Kamera ist sehr leistungsstark.","freq":"low","addedAt":"2026-04","source":"popmots"},{"id":"de_technology_der_videorekorder_6570","cat":"technology","cefr":"B2","word":"der Videorekorder","tr":"video kaset oynatıcı","example":"Der Videorekorder spielt die alten Filme ab.","freq":"low","addedAt":"2026-04","source":"popmots"},{"id":"de_technology_audio_6735","cat":"technology","cefr":"C1","word":"audio","tr":"ses","example":"Das Audio der Präsentation war von hoher Qualität.","freq":"low","addedAt":"2026-04","source":"popmots"},{"id":"de_technology_die_diskette_6818","cat":"technology","cefr":"C1","word":"die Diskette","tr":"disket","example":"Die Diskette ist ein veraltetes Speichermedium.","freq":"low","addedAt":"2026-04","source":"popmots"},{"id":"de_technology_die_klimaanlage_6867","cat":"technology","cefr":"C1","word":"die Klimaanlage","tr":"klima","example":"Die Klimaanlage sorgt für angenehme Temperaturen.","freq":"low","addedAt":"2026-04","source":"popmots"},{"id":"de_technology_die_sicherung_7122","cat":"technology","cefr":"C1","word":"die Sicherung","tr":"sigorta","example":"Die Sicherung ist durchgebrannt und muss ersetzt werden.","freq":"low","addedAt":"2026-04","source":"popmots"},{"id":"de_media_medial_7195","cat":"media","cefr":"C1","word":"medial","tr":"medya","example":"Die medialen Berichterstattungen sind oft einseitig.","freq":"low","addedAt":"2026-04","source":"popmots"},{"id":"de_environment_okologisch_7233","cat":"environment","cefr":"C1","word":"ökologisch","tr":"ekolojik","example":"Ökologische Landwirtschaft ist wichtig für die Umwelt.","freq":"low","addedAt":"2026-04","source":"popmots"},{"id":"de_technology_der_brenner_7237","cat":"technology","cefr":"C1","word":"der Brenner","tr":"meşale","example":"Der Brenner leuchtet in der Dunkelheit.","freq":"low","addedAt":"2026-04","source":"popmots"},{"id":"de_technology_das_intercom_7255","cat":"technology","cefr":"C1","word":"das Intercom","tr":"interkom","example":"Das Intercom-System erleichtert die Kommunikation im Büro.","freq":"low","addedAt":"2026-04","source":"popmots"},{"id":"de_technology_der_kurzschluss_7508","cat":"technology","cefr":"C1","word":"der Kurzschluss","tr":"kısa devre","example":"Ein Kurzschluss kann gefährliche Folgen haben.","freq":"low","addedAt":"2026-04","source":"popmots"},{"id":"de_technology_das_hologramm_7546","cat":"technology","cefr":"C1","word":"das Hologramm","tr":"hologram","example":"Das Hologramm war beeindruckend und realistisch.","freq":"low","addedAt":"2026-04","source":"popmots"},{"id":"de_technology_virtuell_7556","cat":"technology","cefr":"C1","word":"virtuell","tr":"sanal","example":"Das virtuelle Meeting fand heute statt.","freq":"low","addedAt":"2026-04","source":"popmots"},{"id":"de_media_die_veroffentlichung_7666","cat":"media","cefr":"C1","word":"die Veröffentlichung","tr":"yayın","example":"Die Veröffentlichung des Buches war ein großer Erfolg.","freq":"low","addedAt":"2026-04","source":"popmots"},{"id":"de_media_die_einschaltquote_7758","cat":"media","cefr":"C1","word":"die Einschaltquote","tr":"izlenme oranı","example":"Die Einschaltquote der Sendung war überraschend hoch.","freq":"low","addedAt":"2026-04","source":"popmots"},{"id":"de_technology_der_leistungsschalter_7816","cat":"technology","cefr":"C1","word":"der Leistungsschalter","tr":"devre kesici","example":"Der Leistungsschalter schützt die elektrischen Geräte vor Überlastung.","freq":"low","addedAt":"2026-04","source":"popmots"},{"id":"de_technology_die_schnittstelle_7916","cat":"technology","cefr":"C1","word":"die Schnittstelle","tr":"arayüz","example":"Die Schnittstelle zwischen Mensch und Maschine ist entscheidend.","freq":"low","addedAt":"2026-04","source":"popmots"},{"id":"de_technology_elektromagnetisch_7928","cat":"technology","cefr":"C1","word":"elektromagnetisch","tr":"elektromanyetik","example":"Die elektromagnetischen Wellen sind für viele Technologien entscheidend.","freq":"low","addedAt":"2026-04","source":"popmots"},{"id":"de_technology_kompatibel_7990","cat":"technology","cefr":"C1","word":"kompatibel","tr":"uyumlu","example":"Die Software ist nicht kompatibel mit meinem alten Computer.","freq":"low","addedAt":"2026-04","source":"popmots"},{"id":"de_technology_technologisch_7999","cat":"technology","cefr":"C1","word":"technologisch","tr":"teknolojik","example":"Die technologischen Fortschritte verändern unsere Lebensweise.","freq":"low","addedAt":"2026-04","source":"popmots"},{"id":"de_technology_der_anlasser_8084","cat":"technology","cefr":"C1","word":"der Anlasser","tr":"marş motoru","example":"Der Anlasser des Autos funktionierte nicht richtig.","freq":"low","addedAt":"2026-04","source":"popmots"},{"id":"de_technology_der_thermostat_8176","cat":"technology","cefr":"C1","word":"der Thermostat","tr":"termostat","example":"Der Thermostat steuert die Raumtemperatur.","freq":"low","addedAt":"2026-04","source":"popmots"},{"id":"de_technology_die_soundanlage_8265","cat":"technology","cefr":"C1","word":"die Soundanlage","tr":"ses sistemi","example":"Die Soundanlage sorgt für gute Musik beim Fest.","freq":"low","addedAt":"2026-04","source":"popmots"},{"id":"de_technology_der_telex_8273","cat":"technology","cefr":"C1","word":"der Telex","tr":"telex","example":"Der Telex wurde früher für Nachrichten verwendet.","freq":"low","addedAt":"2026-04","source":"popmots"},{"id":"de_technology_hydraulisch_8349","cat":"technology","cefr":"C1","word":"hydraulisch","tr":"hidrolik","example":"Die hydraulischen Systeme sind sehr effizient.","freq":"low","addedAt":"2026-04","source":"popmots"},{"id":"de_technology_elektrisch_erzeugend_8531","cat":"technology","cefr":"C1","word":"elektrisch erzeugend","tr":"elektrik üreten","example":"Das elektrisch erzeugend Gerät spart viel Energie.","freq":"low","addedAt":"2026-04","source":"popmots"},{"id":"de_technology_die_programmierung_8560","cat":"technology","cefr":"C1","word":"die Programmierung","tr":"programlama","example":"Die Programmierung der Software ist sehr komplex.","freq":"low","addedAt":"2026-04","source":"popmots"}]}